mkdocs_table_reader_plugin/__init__.py
mkdocs_table_reader_plugin/markdown.py
mkdocs_table_reader_plugin/plugin.py
mkdocs_table_reader_plugin/readers.py
mkdocs_table_reader_plugin/safe_eval.py
mkdocs_table_reader_plugin/utils.py
mkdocs_table_reader_plugin-3.0.1.dist-info/LICENSE
mkdocs_table_reader_plugin-3.0.1.dist-info/METADATA
mkdocs_table_reader_plugin-3.0.1.dist-info/WHEEL
mkdocs_table_reader_plugin-3.0.1.dist-info/entry_points.txt
mkdocs_table_reader_plugin-3.0.1.dist-info/top_level.txt
mkdocs_table_reader_plugin-3.0.1.dist-info/RECORD
