Metadata-Version: 2.1
Name: mkdocs-table-reader-plugin
Version: 3.0.1
Summary: MkDocs plugin to directly insert tables from files into markdown.
Home-page: https://github.com/timvink/mkdocs-table-reader-plugin
Author: Tim Vink
Author-email: vinktim@gmail.com
License: MIT
Keywords: mkdocs plugin
Classifier: Operating System :: OS Independent
Classifier: Programming Language :: Python
Classifier: Programming Language :: Python :: 3
Classifier: Programming Language :: Python :: 3.8
Classifier: Programming Language :: Python :: 3.9
Classifier: Programming Language :: Python :: 3.10
Classifier: Programming Language :: Python :: 3.11
Classifier: License :: OSI Approved :: MIT License
Requires-Python: >=3.8
License-File: LICENSE
Requires-Dist: mkdocs>=1.0
Requires-Dist: pandas>=1.1
Requires-Dist: tabulate>=0.8.7
Requires-Dist: PyYAML>=5.4.1
